LICENSE
MANIFEST.in
README.md
pyproject.toml
setup.cfg
setup.py
tests/__init__.py
tests/testapp/__init__.py
tests/testapp/manage.py
tests/testapp/core/__init__.py
tests/testapp/core/tests.py
tests/testapp/core/migrations/__init__.py
tests/testapp/testapp/__init__.py
tests/testapp/testapp/asgi.py
tests/testapp/testapp/settings.py
tests/testapp/testapp/urls.py
tests/testapp/testapp/wsgi.py
wagtail_theme_manager.egg-info/PKG-INFO
wagtail_theme_manager.egg-info/SOURCES.txt
wagtail_theme_manager.egg-info/dependency_links.txt
wagtail_theme_manager.egg-info/requires.txt
wagtail_theme_manager.egg-info/top_level.txt
wagtail_themes/__init__.py
wagtail_themes/admin.py
wagtail_themes/apps.py
wagtail_themes/options.py
wagtail_themes/settings_registry.py
wagtail_themes/tests.py
wagtail_themes/views.py
wagtail_themes/blocks/__init__.py
wagtail_themes/blocks/metatags.py
wagtail_themes/blocks/settings.py
wagtail_themes/migrations/0001_initial.py
wagtail_themes/migrations/0002_alter_uiimprovementsettings_styles.py
wagtail_themes/migrations/0003_alter_uiimprovementsettings_styles.py
wagtail_themes/migrations/0004_uiimprovementsettings_components_and_more.py
wagtail_themes/migrations/__init__.py
wagtail_themes/migrations/__pycache__/0001_initial.cpython-311.pyc
wagtail_themes/migrations/__pycache__/0002_alter_uiimprovementsettings_styles.cpython-311.pyc
wagtail_themes/migrations/__pycache__/0003_alter_uiimprovementsettings_styles.cpython-311.pyc
wagtail_themes/migrations/__pycache__/0004_uiimprovementsettings_components_and_more.cpython-311.pyc
wagtail_themes/migrations/__pycache__/__init__.cpython-311.pyc
wagtail_themes/models/__init__.py
wagtail_themes/models/metatags.py
wagtail_themes/models/settings.py
wagtail_themes/static/ui_improvements/css/admin.css
wagtail_themes/templates/ui_improvements/metatags/metatag.html
wagtail_themes/templates/ui_improvements/metatags/metatags.html
wagtail_themes/wagtail_hooks/__init__.py
wagtail_themes/wagtail_hooks/admin.py
wagtail_themes/wagtail_hooks/menu.py